atbu/mp_pipeline/__init__.py
atbu/mp_pipeline/exception.py
atbu/mp_pipeline/mp_global.py
atbu/mp_pipeline/mp_helper.py
atbu/mp_pipeline/mp_pipeline.py
atbu_mp_pipeline_pkg-0.0.10.dist-info/LICENSE
atbu_mp_pipeline_pkg-0.0.10.dist-info/METADATA
atbu_mp_pipeline_pkg-0.0.10.dist-info/WHEEL
atbu_mp_pipeline_pkg-0.0.10.dist-info/top_level.txt
atbu_mp_pipeline_pkg-0.0.10.dist-info/RECORD
