Metadata-Version: 2.1
Name: atbu-mp-pipeline-pkg
Version: 0.0.10
Summary: ATBU atbu.mp_pipeline package, a multiprocessing work item pipeline.
Home-page: https://github.com/AshleyT3/atbu-mp-pipeline
Author: Ashley R. Thomas
Author-email: ashley.r.thomas.701@gmail.com
Project-URL: Bug Tracker, https://github.com/AshleyT3/atbu-mp-pipeline/issues
Classifier: Programming Language :: Python :: 3
Classifier: Programming Language :: Python :: 3.10
Classifier: Programming Language :: Python :: 3.11
Classifier: Programming Language :: Python :: 3.12
Classifier: License :: OSI Approved :: Apache Software License
Classifier: Operating System :: OS Independent
Requires-Python: >=3.10
License-File: LICENSE
Requires-Dist: atbu-common-pkg>=0.0.12
